{
  "livro": "marcos",
  "livroNome": "Marcos",
  "capitulo": 1,
  "testamento": "NT",
  "titulo": "",
  "autor": "João Marcos",
  "versiculos": [
    {
      "numero": 1,
      "versoes": {
        "ARC": "Princípio do evangelho de Jesus Cristo, Filho de Deus."
      },
      "temas": [],
      "versiculosRelacionados": [],
      "faq": []
    },
    {
      "numero": 2,
      "versoes": {
        "ARC": "Conforme está escrito no profeta Isaías: Eis que envio ante a tua face o meu mensageiro, que há de preparar o teu caminho;"
      },
      "temas": [],
      "versiculosRelacionados": [],
      "faq": []
    },
    {
      "numero": 3,
      "versoes": {
        "ARC": "voz do que clama no deserto: Preparai o caminho do Senhor, endireitai as suas veredas;"
      },
      "temas": [],
      "versiculosRelacionados": [],
      "faq": []
    },
    {
      "numero": 4,
      "versoes": {
        "ARC": "assim apareceu João, o Batista, no deserto, pregando o batismo de arrependimento para remissão dos pecados."
      },
      "temas": [],
      "versiculosRelacionados": [],
      "faq": []
    },
    {
      "numero": 5,
      "versoes": {
        "ARC": "E saíam a ter com ele toda a terra da Judéia, e todos os moradores de Jerusalém; e eram por ele batizados no rio Jordão, confessando os seus pecados."
      },
      "temas": [],
      "versiculosRelacionados": [],
      "faq": []
    },
    {
      "numero": 6,
      "versoes": {
        "ARC": "Ora, João usava uma veste de pêlos de camelo, e um cinto de couro em torno de seus lombos, e comia gafanhotos e mel silvestre."
      },
      "temas": [],
      "versiculosRelacionados": [],
      "faq": []
    },
    {
      "numero": 7,
      "versoes": {
        "ARC": "E pregava, dizendo: Após mim vem aquele que é mais poderoso do que eu, de quem não sou digno de, inclinando-me, desatar a correia das alparcas."
      },
      "temas": [],
      "versiculosRelacionados": [],
      "faq": []
    },
    {
      "numero": 8,
      "versoes": {
        "ARC": "Eu vos batizei em água; ele, porém, vos batizará no Espírito Santo."
      },
      "temas": [],
      "versiculosRelacionados": [],
      "faq": []
    },
    {
      "numero": 9,
      "versoes": {
        "ARC": "E aconteceu naqueles dias que veio Jesus de Nazaré da Galiléia, e foi batizado por João no Jordão."
      },
      "temas": [],
      "versiculosRelacionados": [],
      "faq": []
    },
    {
      "numero": 10,
      "versoes": {
        "ARC": "E logo, quando saía da água, viu os céus se abrirem, e o Espírito, qual pomba, a descer sobre ele;"
      },
      "temas": [],
      "versiculosRelacionados": [],
      "faq": []
    },
    {
      "numero": 11,
      "versoes": {
        "ARC": "e ouviu-se dos céus esta voz: Tu és meu Filho amado; em ti me comprazo."
      },
      "temas": [],
      "versiculosRelacionados": [],
      "faq": []
    },
    {
      "numero": 12,
      "versoes": {
        "ARC": "Imediatamente o Espírito o impeliu para o deserto."
      },
      "temas": [],
      "versiculosRelacionados": [],
      "faq": []
    },
    {
      "numero": 13,
      "versoes": {
        "ARC": "E esteve no deserto quarenta dias sentado tentado por Satanás; estava entre as feras, e os anjos o serviam."
      },
      "temas": [],
      "versiculosRelacionados": [],
      "faq": []
    },
    {
      "numero": 14,
      "versoes": {
        "ARC": "Ora, depois que João foi entregue, veio Jesus para a Galiléia pregando o evangelho de Deus"
      },
      "temas": [],
      "versiculosRelacionados": [],
      "faq": []
    },
    {
      "numero": 15,
      "versoes": {
        "ARC": "e dizendo: O tempo está cumprido, e é chegado o reino de Deus. Arrependei-vos, e crede no evangelho."
      },
      "temas": [],
      "versiculosRelacionados": [],
      "faq": []
    },
    {
      "numero": 16,
      "versoes": {
        "ARC": "E, andando junto do mar da Galiléia, viu a Simão, e a André, irmão de Simão, os quais lançavam a rede ao mar, pois eram pescadores."
      },
      "temas": [],
      "versiculosRelacionados": [],
      "faq": []
    },
    {
      "numero": 17,
      "versoes": {
        "ARC": "Disse-lhes Jesus: Vinde após mim, e eu farei que vos torneis pescadores de homens."
      },
      "temas": [],
      "versiculosRelacionados": [],
      "faq": []
    },
    {
      "numero": 18,
      "versoes": {
        "ARC": "Então eles, deixando imediatamente as suas redes, o seguiram."
      },
      "temas": [],
      "versiculosRelacionados": [],
      "faq": []
    },
    {
      "numero": 19,
      "versoes": {
        "ARC": "E ele, passando um pouco adiante, viu Tiago, filho de Zebedeu, e João, seu irmão, que estavam no barco, consertando as redes,"
      },
      "temas": [],
      "versiculosRelacionados": [],
      "faq": []
    },
    {
      "numero": 20,
      "versoes": {
        "ARC": "e logo os chamou; eles, deixando seu pai Zebedeu no barco com os empregados, o seguiram."
      },
      "temas": [],
      "versiculosRelacionados": [],
      "faq": []
    },
    {
      "numero": 21,
      "versoes": {
        "ARC": "Entraram em Cafarnaum; e, logo no sábado, indo ele à sinagoga, pôs-se a ensinar."
      },
      "temas": [],
      "versiculosRelacionados": [],
      "faq": []
    },
    {
      "numero": 22,
      "versoes": {
        "ARC": "E maravilhavam-se da sua doutrina, porque os ensinava como tendo autoridade, e não como os escribas."
      },
      "temas": [],
      "versiculosRelacionados": [],
      "faq": []
    },
    {
      "numero": 23,
      "versoes": {
        "ARC": "Ora, estava na sinagoga um homem possesso dum espírito imundo, o qual gritou:"
      },
      "temas": [],
      "versiculosRelacionados": [],
      "faq": []
    },
    {
      "numero": 24,
      "versoes": {
        "ARC": "Que temos nós contigo, Jesus, nazareno? Vieste destruir-nos? Bem sei quem és: o Santo de Deus."
      },
      "temas": [],
      "versiculosRelacionados": [],
      "faq": []
    },
    {
      "numero": 25,
      "versoes": {
        "ARC": "Mas Jesus o repreendeu, dizendo: Cala-te, e sai dele."
      },
      "temas": [],
      "versiculosRelacionados": [],
      "faq": []
    },
    {
      "numero": 26,
      "versoes": {
        "ARC": "Então o espírito imundo, convulsionando-o e clamando com grande voz, saiu dele."
      },
      "temas": [],
      "versiculosRelacionados": [],
      "faq": []
    },
    {
      "numero": 27,
      "versoes": {
        "ARC": "E todos se maravilharam a ponto de perguntarem entre si, dizendo: Que é isto? Uma nova doutrina com autoridade! Pois ele ordena aos espíritos imundos, e eles lhe obedecem!"
      },
      "temas": [],
      "versiculosRelacionados": [],
      "faq": []
    },
    {
      "numero": 28,
      "versoes": {
        "ARC": "E logo correu a sua fama por toda a região da Galiléia."
      },
      "temas": [],
      "versiculosRelacionados": [],
      "faq": []
    },
    {
      "numero": 29,
      "versoes": {
        "ARC": "Em seguida, saiu da sinagoga e foi a casa de Simão e André com Tiago e João."
      },
      "temas": [],
      "versiculosRelacionados": [],
      "faq": []
    },
    {
      "numero": 30,
      "versoes": {
        "ARC": "A sogra de Simão estava de cama com febre, e logo lhe falaram a respeito dela."
      },
      "temas": [],
      "versiculosRelacionados": [],
      "faq": []
    },
    {
      "numero": 31,
      "versoes": {
        "ARC": "Então Jesus, chegando-se e tomando-a pela mão, a levantou; e a febre a deixou, e ela os servia."
      },
      "temas": [],
      "versiculosRelacionados": [],
      "faq": []
    },
    {
      "numero": 32,
      "versoes": {
        "ARC": "Sendo já tarde, tendo-se posto o sol, traziam-lhe todos os enfermos, e os endemoninhados;"
      },
      "temas": [],
      "versiculosRelacionados": [],
      "faq": []
    },
    {
      "numero": 33,
      "versoes": {
        "ARC": "e toda a cidade estava reunida à porta;"
      },
      "temas": [],
      "versiculosRelacionados": [],
      "faq": []
    },
    {
      "numero": 34,
      "versoes": {
        "ARC": "e ele curou muitos doentes atacados de diversas moléstias, e expulsou muitos demônios; mas não permitia que os demônios falassem, porque o conheciam."
      },
      "temas": [],
      "versiculosRelacionados": [],
      "faq": []
    },
    {
      "numero": 35,
      "versoes": {
        "ARC": "De madrugada, ainda bem escuro, levantou-se, saiu e foi a um lugar deserto, e ali orava."
      },
      "temas": [],
      "versiculosRelacionados": [],
      "faq": []
    },
    {
      "numero": 36,
      "versoes": {
        "ARC": "Foram, pois, Simão e seus companheiros procurá-lo;"
      },
      "temas": [],
      "versiculosRelacionados": [],
      "faq": []
    },
    {
      "numero": 37,
      "versoes": {
        "ARC": "quando o encontraram, disseram-lhe: Todos te buscam."
      },
      "temas": [],
      "versiculosRelacionados": [],
      "faq": []
    },
    {
      "numero": 38,
      "versoes": {
        "ARC": "Respondeu-lhes Jesus: Vamos a outras partes, às povoações vizinhas, para que eu pregue ali também; pois para isso é que vim."
      },
      "temas": [],
      "versiculosRelacionados": [],
      "faq": []
    },
    {
      "numero": 39,
      "versoes": {
        "ARC": "Foi, então, por toda a Galiléia, pregando nas sinagogas deles e expulsando os demônios."
      },
      "temas": [],
      "versiculosRelacionados": [],
      "faq": []
    },
    {
      "numero": 40,
      "versoes": {
        "ARC": "E veio a ele um leproso que, de joelhos, lhe rogava, dizendo: Se quiseres, bem podes tornar-me limpo."
      },
      "temas": [],
      "versiculosRelacionados": [],
      "faq": []
    },
    {
      "numero": 41,
      "versoes": {
        "ARC": "Jesus, pois, compadecido dele, estendendo a mão, tocou-o e disse-lhe: Quero; sê limpo."
      },
      "temas": [],
      "versiculosRelacionados": [],
      "faq": []
    },
    {
      "numero": 42,
      "versoes": {
        "ARC": "Imediatamente desapareceu dele a lepra e ficou limpo."
      },
      "temas": [],
      "versiculosRelacionados": [],
      "faq": []
    },
    {
      "numero": 43,
      "versoes": {
        "ARC": "E Jesus, advertindo-o secretamente, logo o despediu,"
      },
      "temas": [],
      "versiculosRelacionados": [],
      "faq": []
    },
    {
      "numero": 44,
      "versoes": {
        "ARC": "dizendo-lhe: Olha, não digas nada a ninguém; mas vai, mostra-te ao sacerdote e oferece pela tua purificação o que Moisés determinou, para lhes servir de testemunho."
      },
      "temas": [],
      "versiculosRelacionados": [],
      "faq": []
    },
    {
      "numero": 45,
      "versoes": {
        "ARC": "Ele, porém, saindo dali, começou a publicar o caso por toda parte e a divulgá-lo, de modo que Jesus já não podia entrar abertamente numa cidade, mas conservava-se fora em lugares desertos; e de todos os lados iam ter com ele."
      },
      "temas": [],
      "versiculosRelacionados": [],
      "faq": []
    }
  ],
  "explicacao": {
    "introducao": "",
    "contexto": "",
    "aplicacao": ""
  },
  "versiculosDestaque": [],
  "temas": [],
  "versiculosRelacionadosExternos": []
}