{
  "livro": "tiago",
  "livroNome": "Tiago",
  "capitulo": 5,
  "testamento": "NT",
  "titulo": "",
  "autor": "Tiago (irmão de Jesus)",
  "versiculos": [
    {
      "numero": 1,
      "versoes": {
        "ARC": "E agora, vós ricos, chorai e pranteai, por causa das desgraças que vos sobrevirão."
      },
      "temas": [],
      "versiculosRelacionados": [],
      "faq": []
    },
    {
      "numero": 2,
      "versoes": {
        "ARC": "As vossas riquezas estão apodrecidas, e as vossas vestes estão roídas pela traça."
      },
      "temas": [],
      "versiculosRelacionados": [],
      "faq": []
    },
    {
      "numero": 3,
      "versoes": {
        "ARC": "O vosso ouro e a vossa prata estão enferrujados; e a sua ferrugem dará testemunho contra vós, e devorará as vossas carnes como fogo. Entesourastes para os últimos dias."
      },
      "temas": [],
      "versiculosRelacionados": [],
      "faq": []
    },
    {
      "numero": 4,
      "versoes": {
        "ARC": "Eis que o salário que fraudulentamente retivestes aos trabalhadores que ceifaram os vossos campos clama, e os clamores dos ceifeiros têm chegado aos ouvidos do Senhor dos exércitos."
      },
      "temas": [],
      "versiculosRelacionados": [],
      "faq": []
    },
    {
      "numero": 5,
      "versoes": {
        "ARC": "Deliciosamente vivestes sobre a terra, e vos deleitastes; cevastes os vossos corações no dia da matança."
      },
      "temas": [],
      "versiculosRelacionados": [],
      "faq": []
    },
    {
      "numero": 6,
      "versoes": {
        "ARC": "Condenastes e matastes o justo; ele não vos resiste."
      },
      "temas": [],
      "versiculosRelacionados": [],
      "faq": []
    },
    {
      "numero": 7,
      "versoes": {
        "ARC": "Portanto, irmãos, sede pacientes até a vinda do Senhor. Eis que o lavrador espera o precioso fruto da terra, aguardando-o com paciência, até que receba as primeiras e as últimas chuvas."
      },
      "temas": [],
      "versiculosRelacionados": [],
      "faq": []
    },
    {
      "numero": 8,
      "versoes": {
        "ARC": "Sede vós também pacientes; fortalecei os vossos corações, porque a vinda do Senhor está próxima."
      },
      "temas": [],
      "versiculosRelacionados": [],
      "faq": []
    },
    {
      "numero": 9,
      "versoes": {
        "ARC": "Não vos queixeis, irmãos, uns dos outros, para que não sejais julgados. Eis que o juiz está à porta."
      },
      "temas": [],
      "versiculosRelacionados": [],
      "faq": []
    },
    {
      "numero": 10,
      "versoes": {
        "ARC": "Irmãos, tomai como exemplo de sofrimento e paciência os profetas que falaram em nome do Senhor."
      },
      "temas": [],
      "versiculosRelacionados": [],
      "faq": []
    },
    {
      "numero": 11,
      "versoes": {
        "ARC": "Eis que chamamos bem-aventurados os que suportaram aflições. Ouvistes da paciência de Jó, e vistes o fim que o Senhor lhe deu, porque o Senhor é cheio de misericórdia e compaixão."
      },
      "temas": [],
      "versiculosRelacionados": [],
      "faq": []
    },
    {
      "numero": 12,
      "versoes": {
        "ARC": "Mas, sobretudo, meus irmãos, não jureis, nem pelo céu, nem pela terra, nem façais qualquer outro juramento; seja, porém, o vosso sim, sim, e o vosso não, não, para não cairdes em condenação."
      },
      "temas": [],
      "versiculosRelacionados": [],
      "faq": []
    },
    {
      "numero": 13,
      "versoes": {
        "ARC": "Está aflito alguém entre vós? Ore. Está alguém contente? Cante louvores."
      },
      "temas": [],
      "versiculosRelacionados": [],
      "faq": []
    },
    {
      "numero": 14,
      "versoes": {
        "ARC": "Está doente algum de vós? Chame os anciãos da igreja, e estes orem sobre ele, ungido-o com óleo em nome do Senhor;"
      },
      "temas": [],
      "versiculosRelacionados": [],
      "faq": []
    },
    {
      "numero": 15,
      "versoes": {
        "ARC": "e a oração da fé salvará o doente, e o Senhor o levantará; e, se houver cometido pecados, ser-lhe-ão perdoados."
      },
      "temas": [],
      "versiculosRelacionados": [],
      "faq": []
    },
    {
      "numero": 16,
      "versoes": {
        "ARC": "Confessai, portanto, os vossos pecados uns aos outros, e orai uns pelos outros, para serdes curados. A súplica de um justo pode muito na sua atuação."
      },
      "temas": [],
      "versiculosRelacionados": [],
      "faq": []
    },
    {
      "numero": 17,
      "versoes": {
        "ARC": "Elias era homem sujeito às mesmas paixões que nós, e orou com fervor para que não chovesse, e por três anos e seis meses não choveu sobre a terra."
      },
      "temas": [],
      "versiculosRelacionados": [],
      "faq": []
    },
    {
      "numero": 18,
      "versoes": {
        "ARC": "E orou outra vez e o céu deu chuva, e a terra produziu o seu fruto."
      },
      "temas": [],
      "versiculosRelacionados": [],
      "faq": []
    },
    {
      "numero": 19,
      "versoes": {
        "ARC": "Meus irmãos, se alguém dentre vós se desviar da verdade e alguém o converter,"
      },
      "temas": [],
      "versiculosRelacionados": [],
      "faq": []
    },
    {
      "numero": 20,
      "versoes": {
        "ARC": "sabei que aquele que fizer converter um pecador do erro do seu caminho salvará da morte uma alma, e cobrirá uma multidão de pecados."
      },
      "temas": [],
      "versiculosRelacionados": [],
      "faq": []
    }
  ],
  "explicacao": {
    "introducao": "",
    "contexto": "",
    "aplicacao": ""
  },
  "versiculosDestaque": [],
  "temas": [],
  "versiculosRelacionadosExternos": []
}