{
  "livro": "proverbios",
  "livroNome": "Provérbios",
  "capitulo": 12,
  "testamento": "AT",
  "titulo": "",
  "autor": "Salomão e outros",
  "versiculos": [
    {
      "numero": 1,
      "versoes": {
        "ARC": "O que ama a correção ama o conhecimento; mas o que aborrece a repreensão é insensato."
      },
      "temas": [],
      "versiculosRelacionados": [],
      "faq": []
    },
    {
      "numero": 2,
      "versoes": {
        "ARC": "O homem de bem alcançará o favor do Senhor; mas ao homem de perversos desígnios ele condenará."
      },
      "temas": [],
      "versiculosRelacionados": [],
      "faq": []
    },
    {
      "numero": 3,
      "versoes": {
        "ARC": "O homem não se estabelece pela impiedade; a raiz dos justos, porém, nunca será, removida."
      },
      "temas": [],
      "versiculosRelacionados": [],
      "faq": []
    },
    {
      "numero": 4,
      "versoes": {
        "ARC": "A mulher virtuosa é a coroa do seu marido; porém a que procede vergonhosamente é como apodrecimento nos seus ossos."
      },
      "temas": [],
      "versiculosRelacionados": [],
      "faq": []
    },
    {
      "numero": 5,
      "versoes": {
        "ARC": "Os pensamentos do justo são retos; mas os conselhos do ímpio são falsos."
      },
      "temas": [],
      "versiculosRelacionados": [],
      "faq": []
    },
    {
      "numero": 6,
      "versoes": {
        "ARC": "As palavras dos ímpios são emboscadas para derramarem sangue; a boca dos retos, porém, os livrará."
      },
      "temas": [],
      "versiculosRelacionados": [],
      "faq": []
    },
    {
      "numero": 7,
      "versoes": {
        "ARC": "Transtornados serão os ímpios, e não serão mais; porém a casa dos justos permanecerá."
      },
      "temas": [],
      "versiculosRelacionados": [],
      "faq": []
    },
    {
      "numero": 8,
      "versoes": {
        "ARC": "Segundo o seu entendimento é louvado o homem; mas o perverso decoração é desprezado."
      },
      "temas": [],
      "versiculosRelacionados": [],
      "faq": []
    },
    {
      "numero": 9,
      "versoes": {
        "ARC": "Melhor é o que é estimado em pouco e tem servo, do que quem se honra a si mesmo e tem falta de pão."
      },
      "temas": [],
      "versiculosRelacionados": [],
      "faq": []
    },
    {
      "numero": 10,
      "versoes": {
        "ARC": "O justo olha pela vida dos seus animais; porém as entranhas dos ímpios são cruéis."
      },
      "temas": [],
      "versiculosRelacionados": [],
      "faq": []
    },
    {
      "numero": 11,
      "versoes": {
        "ARC": "O que lavra a sua terra se fartará de pão; mas o que segue os ociosos é falto de entendimento."
      },
      "temas": [],
      "versiculosRelacionados": [],
      "faq": []
    },
    {
      "numero": 12,
      "versoes": {
        "ARC": "Deseja o ímpio o despojo dos maus; porém a raiz dos justos produz o seu próprio fruto."
      },
      "temas": [],
      "versiculosRelacionados": [],
      "faq": []
    },
    {
      "numero": 13,
      "versoes": {
        "ARC": "Pela transgressão dos lábios se enlaça o mau; mas o justo escapa da angústia."
      },
      "temas": [],
      "versiculosRelacionados": [],
      "faq": []
    },
    {
      "numero": 14,
      "versoes": {
        "ARC": "Do fruto das suas palavras o homem se farta de bem; e das obras das suas mãos se lhe retribui."
      },
      "temas": [],
      "versiculosRelacionados": [],
      "faq": []
    },
    {
      "numero": 15,
      "versoes": {
        "ARC": "O caminho do insensato é reto aos seus olhos; mas o que dá ouvidos ao conselho é sábio."
      },
      "temas": [],
      "versiculosRelacionados": [],
      "faq": []
    },
    {
      "numero": 16,
      "versoes": {
        "ARC": "A ira do insensato logo se revela; mas o prudente encobre a afronta."
      },
      "temas": [],
      "versiculosRelacionados": [],
      "faq": []
    },
    {
      "numero": 17,
      "versoes": {
        "ARC": "Quem fala a verdade manifesta a justiça; porém a testemunha falsa produz a fraude."
      },
      "temas": [],
      "versiculosRelacionados": [],
      "faq": []
    },
    {
      "numero": 18,
      "versoes": {
        "ARC": "Há palrador cujas palavras ferem como espada; porém a língua dos sábios traz saúde."
      },
      "temas": [],
      "versiculosRelacionados": [],
      "faq": []
    },
    {
      "numero": 19,
      "versoes": {
        "ARC": "O lábio veraz permanece para sempre; mas a língua mentirosa dura só um momento."
      },
      "temas": [],
      "versiculosRelacionados": [],
      "faq": []
    },
    {
      "numero": 20,
      "versoes": {
        "ARC": "Engano há no coração dos que maquinam o mal; mas há gozo para os que aconselham a paz."
      },
      "temas": [],
      "versiculosRelacionados": [],
      "faq": []
    },
    {
      "numero": 21,
      "versoes": {
        "ARC": "Nenhuma desgraça sobrevém ao justo; mas os ímpios ficam cheios de males."
      },
      "temas": [],
      "versiculosRelacionados": [],
      "faq": []
    },
    {
      "numero": 22,
      "versoes": {
        "ARC": "Os lábios mentirosos são abomináveis ao Senhor; mas os que praticam a verdade são o seu deleite."
      },
      "temas": [],
      "versiculosRelacionados": [],
      "faq": []
    },
    {
      "numero": 23,
      "versoes": {
        "ARC": "O homem prudente encobre o conhecimento; mas o coração dos tolos proclama a estultícia."
      },
      "temas": [],
      "versiculosRelacionados": [],
      "faq": []
    },
    {
      "numero": 24,
      "versoes": {
        "ARC": "A mão dos diligentes dominará; mas o indolente será tributário servil."
      },
      "temas": [],
      "versiculosRelacionados": [],
      "faq": []
    },
    {
      "numero": 25,
      "versoes": {
        "ARC": "A ansiedade no coração do homem o abate; mas uma boa palavra o alegra."
      },
      "temas": [],
      "versiculosRelacionados": [],
      "faq": []
    },
    {
      "numero": 26,
      "versoes": {
        "ARC": "O justo é um guia para o seu próximo; mas o caminho dos ímpios os faz errar."
      },
      "temas": [],
      "versiculosRelacionados": [],
      "faq": []
    },
    {
      "numero": 27,
      "versoes": {
        "ARC": "O preguiçoso não apanha a sua caça; mas o bem precioso do homem é para o diligente."
      },
      "temas": [],
      "versiculosRelacionados": [],
      "faq": []
    },
    {
      "numero": 28,
      "versoes": {
        "ARC": "Na vereda da justiça está a vida; e no seu caminho não há morte."
      },
      "temas": [],
      "versiculosRelacionados": [],
      "faq": []
    }
  ],
  "explicacao": {
    "introducao": "",
    "contexto": "",
    "aplicacao": ""
  },
  "versiculosDestaque": [],
  "temas": [],
  "versiculosRelacionadosExternos": []
}