{
  "livro": "eclesiastes",
  "livroNome": "Eclesiastes",
  "capitulo": 8,
  "testamento": "AT",
  "titulo": "",
  "autor": "Salomão",
  "versiculos": [
    {
      "numero": 1,
      "versoes": {
        "ARC": "Quem é como o sábio? e quem sabe a interpretação das coisas? A sabedoria do homem faz brilhar o seu rosto, e com ela a dureza do seu rosto se transforma."
      },
      "temas": [],
      "versiculosRelacionados": [],
      "faq": []
    },
    {
      "numero": 2,
      "versoes": {
        "ARC": "Eu digo: Observa o mandamento do rei, e isso por causa do juramento a Deus."
      },
      "temas": [],
      "versiculosRelacionados": [],
      "faq": []
    },
    {
      "numero": 3,
      "versoes": {
        "ARC": "Não te apresses a sair da presença dele; nem persistas em alguma coisa má; porque ele faz tudo o que lhe agrada."
      },
      "temas": [],
      "versiculosRelacionados": [],
      "faq": []
    },
    {
      "numero": 4,
      "versoes": {
        "ARC": "Porque a palavra do rei é suprema; e quem lhe dirá: que fazes?"
      },
      "temas": [],
      "versiculosRelacionados": [],
      "faq": []
    },
    {
      "numero": 5,
      "versoes": {
        "ARC": "Quem guardar o mandamento não experimentará nenhum mal; e o coração do sábio discernirá o tempo e o juízo."
      },
      "temas": [],
      "versiculosRelacionados": [],
      "faq": []
    },
    {
      "numero": 6,
      "versoes": {
        "ARC": "Porque para todo propósito há tempo e juízo; porquanto a miséria do homem pesa sobre ele."
      },
      "temas": [],
      "versiculosRelacionados": [],
      "faq": []
    },
    {
      "numero": 7,
      "versoes": {
        "ARC": "Porque não sabe o que há de suceder; pois quem lho dará a entender como há de ser?"
      },
      "temas": [],
      "versiculosRelacionados": [],
      "faq": []
    },
    {
      "numero": 8,
      "versoes": {
        "ARC": "Nenhum homem há que tenha domínio sobre o espírito, para o reter; nem que tenha poder sobre o dia da morte; nem há licença em tempo de guerra; nem tampouco a impiedade livrará aquele que a ela está entregue."
      },
      "temas": [],
      "versiculosRelacionados": [],
      "faq": []
    },
    {
      "numero": 9,
      "versoes": {
        "ARC": "Tudo isto tenho observado enquanto aplicava o meu coração a toda obra que se faz debaixo do sol; tempo há em que um homem tem domínio sobre outro homem para o seu próprio dano."
      },
      "temas": [],
      "versiculosRelacionados": [],
      "faq": []
    },
    {
      "numero": 10,
      "versoes": {
        "ARC": "Vi também os ímpios sepultados, os que antes entravam e saíam do lugar santo; e foram esquecidos na cidade onde haviam assim procedido; também isso é vaidade."
      },
      "temas": [],
      "versiculosRelacionados": [],
      "faq": []
    },
    {
      "numero": 11,
      "versoes": {
        "ARC": "Porquanto não se executa logo o juízo sobre a má obra, o coração dos filhos dos homens está inteiramente disposto para praticar o mal."
      },
      "temas": [],
      "versiculosRelacionados": [],
      "faq": []
    },
    {
      "numero": 12,
      "versoes": {
        "ARC": "Ainda que o pecador faça o mal cem vezes, e os dias se lhe prolonguem, contudo eu sei com certeza que bem sucede aos que temem a Deus, porque temem diante dele;"
      },
      "temas": [],
      "versiculosRelacionados": [],
      "faq": []
    },
    {
      "numero": 13,
      "versoes": {
        "ARC": "ao ímpio, porém, não irá bem, e ele não prolongará os seus dias, que são como a sombra; porque ele não teme diante de Deus."
      },
      "temas": [],
      "versiculosRelacionados": [],
      "faq": []
    },
    {
      "numero": 14,
      "versoes": {
        "ARC": "Ainda há outra vaidade que se faz sobre a terra: há justos a quem sucede segundo as obras dos ímpios, e há ímpios a quem sucede segundo as obras dos justos. Eu disse que também isso é vaidade."
      },
      "temas": [],
      "versiculosRelacionados": [],
      "faq": []
    },
    {
      "numero": 15,
      "versoes": {
        "ARC": "Exalto, pois, a alegria, porquanto o homem nenhuma coisa melhor tem debaixo do sol do que comer, beber e alegrar-se; porque isso o acompanhará no seu trabalho nos dias da sua vida que Deus lhe dá debaixo do sol."
      },
      "temas": [],
      "versiculosRelacionados": [],
      "faq": []
    },
    {
      "numero": 16,
      "versoes": {
        "ARC": "Quando apliquei o meu coração a conhecer a sabedoria, e a ver o trabalho que se faz sobre a terra {pois homens há que nem de dia nem de noite conseguem dar sono aos seus olhos},"
      },
      "temas": [],
      "versiculosRelacionados": [],
      "faq": []
    },
    {
      "numero": 17,
      "versoes": {
        "ARC": "então contemplei toda obra de Deus, e vi que o homem não pode compreender a obra que se faz debaixo do sol; pois por mais que o homem trabalhe para a descobrir, não a achará; embora o sábio queira conhecê-la, nem por isso a poderá compreender."
      },
      "temas": [],
      "versiculosRelacionados": [],
      "faq": []
    }
  ],
  "explicacao": {
    "introducao": "",
    "contexto": "",
    "aplicacao": ""
  },
  "versiculosDestaque": [],
  "temas": [],
  "versiculosRelacionadosExternos": []
}