{
  "livro": "mateus",
  "livroNome": "Mateus",
  "capitulo": 14,
  "testamento": "NT",
  "titulo": "",
  "autor": "Mateus (apóstolo)",
  "versiculos": [
    {
      "numero": 1,
      "versoes": {
        "ARC": "Naquele tempo Herodes, o tetrarca, ouviu a fama de Jesus,"
      },
      "temas": [],
      "versiculosRelacionados": [],
      "faq": []
    },
    {
      "numero": 2,
      "versoes": {
        "ARC": "e disse aos seus cortesãos: Este é João, o Batista; ele ressuscitou dentre os mortos, e por isso estes poderes milagrosos operam nele."
      },
      "temas": [],
      "versiculosRelacionados": [],
      "faq": []
    },
    {
      "numero": 3,
      "versoes": {
        "ARC": "Pois Herodes havia prendido a João, e, maniatando-o, o guardara no cárcere, por causa de Herodias, mulher de seu irmão Felipe;"
      },
      "temas": [],
      "versiculosRelacionados": [],
      "faq": []
    },
    {
      "numero": 4,
      "versoes": {
        "ARC": "porque João lhe dizia: Não te é lícito possuí-la."
      },
      "temas": [],
      "versiculosRelacionados": [],
      "faq": []
    },
    {
      "numero": 5,
      "versoes": {
        "ARC": "E queria matá-lo, mas temia o povo; porque o tinham como profeta."
      },
      "temas": [],
      "versiculosRelacionados": [],
      "faq": []
    },
    {
      "numero": 6,
      "versoes": {
        "ARC": "Festejando-se, porém, o dia natalício de Herodes, a filha de Herodias dançou no meio dos convivas, e agradou a Herodes,"
      },
      "temas": [],
      "versiculosRelacionados": [],
      "faq": []
    },
    {
      "numero": 7,
      "versoes": {
        "ARC": "pelo que este prometeu com juramento dar-lhe tudo o que pedisse."
      },
      "temas": [],
      "versiculosRelacionados": [],
      "faq": []
    },
    {
      "numero": 8,
      "versoes": {
        "ARC": "E instigada por sua mãe, disse ela: Dá-me aqui num prato a cabeça de João, o Batista."
      },
      "temas": [],
      "versiculosRelacionados": [],
      "faq": []
    },
    {
      "numero": 9,
      "versoes": {
        "ARC": "Entristeceu-se, então, o rei; mas, por causa do juramento, e dos que estavam à mesa com ele, ordenou que se lhe desse,"
      },
      "temas": [],
      "versiculosRelacionados": [],
      "faq": []
    },
    {
      "numero": 10,
      "versoes": {
        "ARC": "e mandou degolar a João no cárcere;"
      },
      "temas": [],
      "versiculosRelacionados": [],
      "faq": []
    },
    {
      "numero": 11,
      "versoes": {
        "ARC": "e a cabeça foi trazida num prato, e dada à jovem, e ela a levou para a sua mãe."
      },
      "temas": [],
      "versiculosRelacionados": [],
      "faq": []
    },
    {
      "numero": 12,
      "versoes": {
        "ARC": "Então vieram os seus discípulos, levaram o corpo e o sepultaram; e foram anunciá-lo a Jesus."
      },
      "temas": [],
      "versiculosRelacionados": [],
      "faq": []
    },
    {
      "numero": 13,
      "versoes": {
        "ARC": "Jesus, ouvindo isto, retirou-se dali num barco, para um, lugar deserto, à parte; e quando as multidões o souberam, seguiram-no a pé desde as cidades."
      },
      "temas": [],
      "versiculosRelacionados": [],
      "faq": []
    },
    {
      "numero": 14,
      "versoes": {
        "ARC": "E ele, ao desembarcar, viu uma grande multidão; e, compadecendo-se dela, curou os seus enfermos."
      },
      "temas": [],
      "versiculosRelacionados": [],
      "faq": []
    },
    {
      "numero": 15,
      "versoes": {
        "ARC": "Chegada a tarde, aproximaram-se dele os discípulos, dizendo: O lugar é deserto, e a hora é já passada; despede as multidões, para que vão às aldeias, e comprem o que comer."
      },
      "temas": [],
      "versiculosRelacionados": [],
      "faq": []
    },
    {
      "numero": 16,
      "versoes": {
        "ARC": "Jesus, porém, lhes disse: Não precisam ir embora; dai-lhes vós de comer."
      },
      "temas": [],
      "versiculosRelacionados": [],
      "faq": []
    },
    {
      "numero": 17,
      "versoes": {
        "ARC": "Então eles lhe disseram: Não temos aqui senão cinco pães e dois peixes."
      },
      "temas": [],
      "versiculosRelacionados": [],
      "faq": []
    },
    {
      "numero": 18,
      "versoes": {
        "ARC": "E ele disse: trazei-mos aqui."
      },
      "temas": [],
      "versiculosRelacionados": [],
      "faq": []
    },
    {
      "numero": 19,
      "versoes": {
        "ARC": "Tendo mandado às multidões que se reclinassem sobre a relva, tomou os cinco pães e os dois peixes e, erguendo os olhos ao céu, os abençoou; e partindo os pães, deu-os aos discípulos, e os discípulos às multidões."
      },
      "temas": [],
      "versiculosRelacionados": [],
      "faq": []
    },
    {
      "numero": 20,
      "versoes": {
        "ARC": "Todos comeram e se fartaram; e dos pedaços que sobejaram levantaram doze cestos cheios."
      },
      "temas": [],
      "versiculosRelacionados": [],
      "faq": []
    },
    {
      "numero": 21,
      "versoes": {
        "ARC": "Ora, os que comeram foram cerca de cinco mil homens, além de mulheres e crianças."
      },
      "temas": [],
      "versiculosRelacionados": [],
      "faq": []
    },
    {
      "numero": 22,
      "versoes": {
        "ARC": "Logo em seguida obrigou os seus discípulos a entrar no barco, e passar adiante dele para o outro lado, enquanto ele despedia as multidões."
      },
      "temas": [],
      "versiculosRelacionados": [],
      "faq": []
    },
    {
      "numero": 23,
      "versoes": {
        "ARC": "Tendo-as despedido, subiu ao monte para orar à parte. Ao anoitecer, estava ali sozinho."
      },
      "temas": [],
      "versiculosRelacionados": [],
      "faq": []
    },
    {
      "numero": 24,
      "versoes": {
        "ARC": "Entrementes, o barco já estava a muitos estádios da terra, açoitado pelas ondas; porque o vento era contrário."
      },
      "temas": [],
      "versiculosRelacionados": [],
      "faq": []
    },
    {
      "numero": 25,
      "versoes": {
        "ARC": "À quarta vigília da noite, foi Jesus ter com eles, andando sobre o mar."
      },
      "temas": [],
      "versiculosRelacionados": [],
      "faq": []
    },
    {
      "numero": 26,
      "versoes": {
        "ARC": "Os discípulos, porém, ao vê-lo andando sobre o mar, assustaram-se e disseram: É um fantasma. E gritaram de medo."
      },
      "temas": [],
      "versiculosRelacionados": [],
      "faq": []
    },
    {
      "numero": 27,
      "versoes": {
        "ARC": "Jesus, porém, imediatamente lhes falou, dizendo: Tende ânimo; sou eu; não temais."
      },
      "temas": [],
      "versiculosRelacionados": [],
      "faq": []
    },
    {
      "numero": 28,
      "versoes": {
        "ARC": "Respondeu-lhe Pedro: Senhor! se és tu, manda-me ir ter contigo sobre as águas."
      },
      "temas": [],
      "versiculosRelacionados": [],
      "faq": []
    },
    {
      "numero": 29,
      "versoes": {
        "ARC": "Disse-lhe ele: Vem. Pedro, descendo do barco, e andando sobre as águas, foi ao encontro de Jesus."
      },
      "temas": [],
      "versiculosRelacionados": [],
      "faq": []
    },
    {
      "numero": 30,
      "versoes": {
        "ARC": "Mas, sentindo o vento, teve medo; e, começando a submergir, clamou: Senhor, salva-me."
      },
      "temas": [],
      "versiculosRelacionados": [],
      "faq": []
    },
    {
      "numero": 31,
      "versoes": {
        "ARC": "Imediatamente estendeu Jesus a mão, segurou-o, e disse-lhe: Homem de pouca fé, por que duvidaste?"
      },
      "temas": [],
      "versiculosRelacionados": [],
      "faq": []
    },
    {
      "numero": 32,
      "versoes": {
        "ARC": "E logo que subiram para o barco, o vento cessou."
      },
      "temas": [],
      "versiculosRelacionados": [],
      "faq": []
    },
    {
      "numero": 33,
      "versoes": {
        "ARC": "Então os que estavam no barco adoraram-no, dizendo: Verdadeiramente tu és Filho de Deus."
      },
      "temas": [],
      "versiculosRelacionados": [],
      "faq": []
    },
    {
      "numero": 34,
      "versoes": {
        "ARC": "Ora, terminada a travessia, chegaram à terra em Genezaré."
      },
      "temas": [],
      "versiculosRelacionados": [],
      "faq": []
    },
    {
      "numero": 35,
      "versoes": {
        "ARC": "Quando os homens daquele lugar o reconheceram, mandaram por toda aquela circunvizinhança, e trouxeram-lhe todos os enfermos;"
      },
      "temas": [],
      "versiculosRelacionados": [],
      "faq": []
    },
    {
      "numero": 36,
      "versoes": {
        "ARC": "e rogaram-lhe que apenas os deixasse tocar a orla do seu manto; e todos os que a tocaram ficaram curados."
      },
      "temas": [],
      "versiculosRelacionados": [],
      "faq": []
    }
  ],
  "explicacao": {
    "introducao": "",
    "contexto": "",
    "aplicacao": ""
  },
  "versiculosDestaque": [],
  "temas": [],
  "versiculosRelacionadosExternos": []
}