{
  "livro": "salmos",
  "livroNome": "Salmos",
  "capitulo": 18,
  "testamento": "AT",
  "titulo": "",
  "autor": "Davi e outros",
  "versiculos": [
    {
      "numero": 1,
      "versoes": {
        "ARC": "Eu te amo, ó Senhor, força minha."
      },
      "temas": [],
      "versiculosRelacionados": [],
      "faq": []
    },
    {
      "numero": 2,
      "versoes": {
        "ARC": "O Senhor é a minha rocha, a minha fortaleza e o meu libertador; o meu Deus, o meu rochedo, em quem me refúgio; o meu escudo, a força da minha salvação, e o meu alto refúgio."
      },
      "temas": [],
      "versiculosRelacionados": [],
      "faq": []
    },
    {
      "numero": 3,
      "versoes": {
        "ARC": "Invoco o Senhor, que é digno de louvor, e sou salvo dos meus inimigos."
      },
      "temas": [],
      "versiculosRelacionados": [],
      "faq": []
    },
    {
      "numero": 4,
      "versoes": {
        "ARC": "Cordas de morte me cercaram, e torrentes de perdição me amedrontaram."
      },
      "temas": [],
      "versiculosRelacionados": [],
      "faq": []
    },
    {
      "numero": 5,
      "versoes": {
        "ARC": "Cordas de Seol me cingiram, laços de morte me surpreenderam."
      },
      "temas": [],
      "versiculosRelacionados": [],
      "faq": []
    },
    {
      "numero": 6,
      "versoes": {
        "ARC": "Na minha angústia invoquei o Senhor, sim, clamei ao meu Deus; do seu templo ouviu ele a minha voz; o clamor que eu lhe fiz chegou aos seus ouvidos."
      },
      "temas": [],
      "versiculosRelacionados": [],
      "faq": []
    },
    {
      "numero": 7,
      "versoes": {
        "ARC": "Então a terra se abalou e tremeu, e os fundamentos dos montes também se moveram e se abalaram, porquanto ele se indignou."
      },
      "temas": [],
      "versiculosRelacionados": [],
      "faq": []
    },
    {
      "numero": 8,
      "versoes": {
        "ARC": "Das suas narinas subiu fumaça, e da sua boca saiu fogo devorador; dele saíram brasas ardentes."
      },
      "temas": [],
      "versiculosRelacionados": [],
      "faq": []
    },
    {
      "numero": 9,
      "versoes": {
        "ARC": "Ele abaixou os céus e desceu; trevas espessas havia debaixo de seus pés."
      },
      "temas": [],
      "versiculosRelacionados": [],
      "faq": []
    },
    {
      "numero": 10,
      "versoes": {
        "ARC": "Montou num querubim, e voou; sim, voou sobre as asas do vento."
      },
      "temas": [],
      "versiculosRelacionados": [],
      "faq": []
    },
    {
      "numero": 11,
      "versoes": {
        "ARC": "Fez das trevas o seu retiro secreto; o pavilhão que o cercava era a escuridão das águas e as espessas nuvens do céu."
      },
      "temas": [],
      "versiculosRelacionados": [],
      "faq": []
    },
    {
      "numero": 12,
      "versoes": {
        "ARC": "Do resplendor da sua presença saíram, pelas suas espessas nuvens, saraiva e brasas de fogo."
      },
      "temas": [],
      "versiculosRelacionados": [],
      "faq": []
    },
    {
      "numero": 13,
      "versoes": {
        "ARC": "O Senhor trovejou a sua voz; e havia saraiva e brasas de fogo."
      },
      "temas": [],
      "versiculosRelacionados": [],
      "faq": []
    },
    {
      "numero": 14,
      "versoes": {
        "ARC": "Despediu as suas setas, e os espalhou; multiplicou raios, e os perturbou."
      },
      "temas": [],
      "versiculosRelacionados": [],
      "faq": []
    },
    {
      "numero": 15,
      "versoes": {
        "ARC": "Então foram vistos os leitos das águas, e foram descobertos os fundamentos do mundo, à tua repreensão, Senhor, ao sopro do vento das tuas narinas."
      },
      "temas": [],
      "versiculosRelacionados": [],
      "faq": []
    },
    {
      "numero": 16,
      "versoes": {
        "ARC": "Do alto estendeu o braço e me tomou; tirou-me das muitas águas."
      },
      "temas": [],
      "versiculosRelacionados": [],
      "faq": []
    },
    {
      "numero": 17,
      "versoes": {
        "ARC": "Livrou-me do meu inimigo forte e daqueles que me odiavam; pois eram mais poderosos do que eu."
      },
      "temas": [],
      "versiculosRelacionados": [],
      "faq": []
    },
    {
      "numero": 18,
      "versoes": {
        "ARC": "Surpreenderam-me eles no dia da minha calamidade, mas o Senhor foi o meu amparo."
      },
      "temas": [],
      "versiculosRelacionados": [],
      "faq": []
    },
    {
      "numero": 19,
      "versoes": {
        "ARC": "Trouxe-me para um lugar espaçoso; livrou-me, porque tinha prazer em mim."
      },
      "temas": [],
      "versiculosRelacionados": [],
      "faq": []
    },
    {
      "numero": 20,
      "versoes": {
        "ARC": "Recompensou-me o Senhor conforme a minha justiça, retribuiu-me conforme a pureza das minhas mãos."
      },
      "temas": [],
      "versiculosRelacionados": [],
      "faq": []
    },
    {
      "numero": 21,
      "versoes": {
        "ARC": "Pois tenho guardado os caminhos do Senhor, e não me apartei impiamente do meu Deus."
      },
      "temas": [],
      "versiculosRelacionados": [],
      "faq": []
    },
    {
      "numero": 22,
      "versoes": {
        "ARC": "Porque todas as suas ordenanças estão diante de mim, e nunca afastei de mim os seus estatutos."
      },
      "temas": [],
      "versiculosRelacionados": [],
      "faq": []
    },
    {
      "numero": 23,
      "versoes": {
        "ARC": "Também fui irrepreensível diante dele, e me guardei da iniqüidade."
      },
      "temas": [],
      "versiculosRelacionados": [],
      "faq": []
    },
    {
      "numero": 24,
      "versoes": {
        "ARC": "Pelo que o Senhor me recompensou conforme a minha justiça, conforme a pureza de minhas mãos perante os seus olhos."
      },
      "temas": [],
      "versiculosRelacionados": [],
      "faq": []
    },
    {
      "numero": 25,
      "versoes": {
        "ARC": "Para com o benigno te mostras benigno, e para com o homem perfeito te mostras perfeito."
      },
      "temas": [],
      "versiculosRelacionados": [],
      "faq": []
    },
    {
      "numero": 26,
      "versoes": {
        "ARC": "Para com o puro te mostras puro, e para com o perverso te mostras contrário."
      },
      "temas": [],
      "versiculosRelacionados": [],
      "faq": []
    },
    {
      "numero": 27,
      "versoes": {
        "ARC": "Porque tu livras o povo aflito, mas os olhos altivos tu os abates."
      },
      "temas": [],
      "versiculosRelacionados": [],
      "faq": []
    },
    {
      "numero": 28,
      "versoes": {
        "ARC": "Sim, tu acendes a minha candeia; o Senhor meu Deus alumia as minhas trevas."
      },
      "temas": [],
      "versiculosRelacionados": [],
      "faq": []
    },
    {
      "numero": 29,
      "versoes": {
        "ARC": "Com o teu auxílio dou numa tropa; com o meu Deus salto uma muralha."
      },
      "temas": [],
      "versiculosRelacionados": [],
      "faq": []
    },
    {
      "numero": 30,
      "versoes": {
        "ARC": "Quanto a Deus, o seu caminho é perfeito; a promessa do Senhor é provada; ele é um escudo para todos os que nele confiam."
      },
      "temas": [],
      "versiculosRelacionados": [],
      "faq": []
    },
    {
      "numero": 31,
      "versoes": {
        "ARC": "Pois, quem é Deus senão o Senhor? e quem é rochedo senão o nosso Deus?"
      },
      "temas": [],
      "versiculosRelacionados": [],
      "faq": []
    },
    {
      "numero": 32,
      "versoes": {
        "ARC": "Ele é o Deus que me cinge de força e torna perfeito o meu caminho;"
      },
      "temas": [],
      "versiculosRelacionados": [],
      "faq": []
    },
    {
      "numero": 33,
      "versoes": {
        "ARC": "faz os meus pés como os das corças, e me coloca em segurança nos meus lugares altos."
      },
      "temas": [],
      "versiculosRelacionados": [],
      "faq": []
    },
    {
      "numero": 34,
      "versoes": {
        "ARC": "Adestra as minhas mãos para a peleja, de sorte que os meus braços vergam um arco de bronze."
      },
      "temas": [],
      "versiculosRelacionados": [],
      "faq": []
    },
    {
      "numero": 35,
      "versoes": {
        "ARC": "Também me deste o escudo da tua salvação; a tua mão direita me sustém, e a tua clemência me engrandece."
      },
      "temas": [],
      "versiculosRelacionados": [],
      "faq": []
    },
    {
      "numero": 36,
      "versoes": {
        "ARC": "Alargas o caminho diante de mim, e os meus pés não resvalam."
      },
      "temas": [],
      "versiculosRelacionados": [],
      "faq": []
    },
    {
      "numero": 37,
      "versoes": {
        "ARC": "Persigo os meus inimigos, e os alcanço; não volto senão depois de os ter consumido."
      },
      "temas": [],
      "versiculosRelacionados": [],
      "faq": []
    },
    {
      "numero": 38,
      "versoes": {
        "ARC": "Atravesso-os, de modo que nunca mais se podem levantar; caem debaixo dos meus pés."
      },
      "temas": [],
      "versiculosRelacionados": [],
      "faq": []
    },
    {
      "numero": 39,
      "versoes": {
        "ARC": "Pois me cinges de força para a peleja; prostras debaixo de mim aqueles que contra mim se levantam."
      },
      "temas": [],
      "versiculosRelacionados": [],
      "faq": []
    },
    {
      "numero": 40,
      "versoes": {
        "ARC": "Fazes também que os meus inimigos me dêem as costas; aos que me odeiam eu os destruo."
      },
      "temas": [],
      "versiculosRelacionados": [],
      "faq": []
    },
    {
      "numero": 41,
      "versoes": {
        "ARC": "Clamam, porém não há libertador; clamam ao Senhor, mas ele não lhes responde."
      },
      "temas": [],
      "versiculosRelacionados": [],
      "faq": []
    },
    {
      "numero": 42,
      "versoes": {
        "ARC": "Então os esmiuço como o pó diante do vento; lanço-os fora como a lama das ruas."
      },
      "temas": [],
      "versiculosRelacionados": [],
      "faq": []
    },
    {
      "numero": 43,
      "versoes": {
        "ARC": "Livras-me das contendas do povo, e me fazes cabeça das nações; um povo que eu não conhecia se me sujeita."
      },
      "temas": [],
      "versiculosRelacionados": [],
      "faq": []
    },
    {
      "numero": 44,
      "versoes": {
        "ARC": "Ao ouvirem de mim, logo me obedecem; com lisonja os estrangeiros se me submetem."
      },
      "temas": [],
      "versiculosRelacionados": [],
      "faq": []
    },
    {
      "numero": 45,
      "versoes": {
        "ARC": "Os estrangeiros desfalecem e, tremendo, saem dos seus esconderijos."
      },
      "temas": [],
      "versiculosRelacionados": [],
      "faq": []
    },
    {
      "numero": 46,
      "versoes": {
        "ARC": "Vive o Senhor; bendita seja a minha rocha, e exaltado seja o Deus da minha salvação,"
      },
      "temas": [],
      "versiculosRelacionados": [],
      "faq": []
    },
    {
      "numero": 47,
      "versoes": {
        "ARC": "o Deus que me dá vingança, e sujeita os povos debaixo de mim,"
      },
      "temas": [],
      "versiculosRelacionados": [],
      "faq": []
    },
    {
      "numero": 48,
      "versoes": {
        "ARC": "que me livra de meus inimigos; sim, tu me exaltas sobre os que se levantam contra mim; tu me livras do homem violento."
      },
      "temas": [],
      "versiculosRelacionados": [],
      "faq": []
    },
    {
      "numero": 49,
      "versoes": {
        "ARC": "Pelo que, ó Senhor, te louvarei entre as nações, e entoarei louvores ao teu nome."
      },
      "temas": [],
      "versiculosRelacionados": [],
      "faq": []
    },
    {
      "numero": 50,
      "versoes": {
        "ARC": "Ele dá grande livramento ao seu rei, e usa de benignidade para com o seu ungido, para com Davi e sua posteridade, para sempre."
      },
      "temas": [],
      "versiculosRelacionados": [],
      "faq": []
    }
  ],
  "explicacao": {
    "introducao": "",
    "contexto": "",
    "aplicacao": ""
  },
  "versiculosDestaque": [],
  "temas": [],
  "versiculosRelacionadosExternos": []
}